[
  {
    "type": "construction_group",
    "id": "GS_bulid_downstair",
    "name": "建设：下行楼梯"
  },
  {
    "type": "construction_group",
    "id": "GS_bulid_upstair",
    "name": "建设：上行楼梯"
  },
  {
    "type": "construction_group",
    "id": "bulid_pwd",
    "name": "建设：平屋顶"
  },
  {
    "type": "construction_group",
    "id": "bulid_pwd_1",
    "name": "建设：平屋顶"
  },
  {
    "type": "construction_group",
    "id": "bulid_tudui",
    "name": "建造：土堆"
  },
  {
    "type": "construction_group",
    "id": "bulid_putu",
    "name": "建设：铺土"
  }
]